cli_logger/__init__.py
cli_logger/logger.py
cli_logger/usage_example.py
atari_monk_cli_logger-0.1.1.dist-info/METADATA
atari_monk_cli_logger-0.1.1.dist-info/WHEEL
atari_monk_cli_logger-0.1.1.dist-info/top_level.txt
atari_monk_cli_logger-0.1.1.dist-info/RECORD
